{
  "reel": 1,
  "hook": "SÓ 1% ACERTA AS 3",
  "scenes": [
    {
      "id": 5201,
      "episode": "friends-s01e13",
      "en": "- Oh, so you think I'm a failure? - Isn't he good?",
      "blankWord": "failure",
      "correctIndex": 3,
      "clipDurationFrames": 76
    },
    {
      "id": 5381,
      "episode": "friends-s01e13",
      "en": "You're not? See, that's why you're so great.",
      "blankWord": "great",
      "correctIndex": 0,
      "clipDurationFrames": 73
    },
    {
      "id": 5167,
      "episode": "friends-s01e13",
      "en": "He's, like, actually some spy working for the CIA.",
      "blankWord": "spy",
      "correctIndex": 0,
      "clipDurationFrames": 99
    }
  ],
  "generatedAt": "2026-04-05T05:46:17.515Z"
}